plain/mail/README.md
plain/mail/__init__.py
plain/mail/default_settings.py
plain/mail/message.py
plain/mail/utils.py
plain/mail/backends/__init__.py
plain/mail/backends/base.py
plain/mail/backends/console.py
plain/mail/backends/filebased.py
plain/mail/backends/smtp.py
plain/mail/backends/testing.py
plain_mail-0.7.0.dist-info/METADATA
plain_mail-0.7.0.dist-info/WHEEL
plain_mail-0.7.0.dist-info/licenses/LICENSE
plain_mail-0.7.0.dist-info/RECORD
