Metadata-Version: 2.4
Name: plain.mail
Version: 0.7.0
Summary: Email sending for Plain.
Author-email: Dave Gaeddert <dave.gaeddert@dropseed.dev>
License-Expression: BSD-3-Clause
License-File: LICENSE
Requires-Python: >=3.11
Requires-Dist: plain<1.0.0
